dongsw/__init__.py
dongsw/extension/__init__.py
dongsw/extension/jqfactor/__init__.py
dongsw/extension/pandas/__init__.py
dongsw/extension/pandas/_pandas.py
dongsw/extension/sklearn/__init__.py
dongsw/extension/sklearn/metrics/__init__.py
dongsw/extension/sklearn/metrics/_metrics.py
dongsw/util/__init__.py
dongsw/util/lists.py
dongsw-1.1.7.dist-info/METADATA
dongsw-1.1.7.dist-info/WHEEL
dongsw-1.1.7.dist-info/top_level.txt
dongsw-1.1.7.dist-info/RECORD
