Metadata-Version: 2.1
Name: dongsw
Version: 1.1.7
Summary: 自用
Home-page: https://github.com/semirol/dsw
Author: dongshanwei
Author-email: 350395090@qq.com
License: UNKNOWN
Platform: UNKNOWN
Classifier: Programming Language :: Python :: 3
Classifier: License :: OSI Approved :: MIT License
Classifier: Operating System :: OS Independent
Requires-Python: >=3.6
